nvMatmulHeuristics/__init__.py
nvMatmulHeuristics/nvMatmulHeuristics.py
nvidia/nvMatmulHeuristics/include/nvMatmulHeuristics.h
nvidia/nvMatmulHeuristics/lib/libnvMatmulHeuristics.so.0
nvidia_matmul_heuristics-0.1.0.24.dist-info/METADATA
nvidia_matmul_heuristics-0.1.0.24.dist-info/WHEEL
nvidia_matmul_heuristics-0.1.0.24.dist-info/top_level.txt
nvidia_matmul_heuristics-0.1.0.24.dist-info/RECORD
nvidia_matmul_heuristics-0.1.0.24.dist-info/licenses/LICENSE.txt
