Metadata-Version: 2.4
Name: nvidia-matmul-heuristics
Version: 0.1.0.24
Summary: NVIDIA heuristics library
Author-email: NVIDIA CUDA Installer Team <cuda_installer@nvidia.com>
License-Expression: LicenseRef-NVIDIA-nvMatmulHeuristics-License
Project-URL: Documentation, https://docs.nvidia.com/cuda/nvMatmulHeuristics/
Keywords: cuda,nvidia,heuristics
Classifier: Development Status :: 4 - Beta
Classifier: Environment :: GPU :: NVIDIA CUDA
Classifier: Intended Audience :: Developers
Classifier: Intended Audience :: Education
Classifier: Intended Audience :: Science/Research
Classifier: Natural Language :: English
Classifier: Operating System :: POSIX :: Linux
Classifier: Programming Language :: C
Classifier: Programming Language :: C++
Classifier: Topic :: Scientific/Engineering
Classifier: Topic :: Scientific/Engineering :: Artificial Intelligence
Classifier: Topic :: Scientific/Engineering :: Mathematics
Classifier: Topic :: Software Development
Classifier: Topic :: Software Development :: Libraries
Requires-Python: >=3.9.0
License-File: LICENSE.txt
Dynamic: license-file
